{"dependencies":[{"name":"/Users/senecamac1/henry/playing-with-tensorflow/fitting-a-curve/package.json","includedInParent":true,"mtime":1522495589000},{"name":"/Users/senecamac1/henry/playing-with-tensorflow/fitting-a-curve/node_modules/vega-canvas/package.json","includedInParent":true,"mtime":1517336212000},{"name":"canvas","optional":true,"loc":{"line":5,"column":23}},{"name":"canvas-prebuilt","optional":true,"loc":{"line":10,"column":25}}],"generated":{"js":"'use strict';\n\nObject.defineProperty(exports, \"__esModule\", {\n  value: true\n});\nexports.nodeCanvas = nodeCanvas;\nexports.nodeImage = nodeImage;\nvar NodeCanvas;\n\ntry {\n  // try to load canvas module\n  NodeCanvas = require('canvas');\n  if (!NodeCanvas) throw 1;\n} catch (e) {\n  try {\n    // if canvas fails, try to load canvas-prebuilt\n    NodeCanvas = require('canvas-prebuilt');\n  } catch (e2) {\n    // if all options fail, set to null\n    NodeCanvas = null;\n  }\n}\n\nfunction nodeCanvas(w, h) {\n  if (NodeCanvas) {\n    try {\n      return new NodeCanvas(w, h);\n    } catch (e) {\n      // do nothing, return null on error\n    }\n  }\n  return null;\n}\n\nfunction nodeImage() {\n  return NodeCanvas && NodeCanvas.Image || null;\n}"},"hash":"ffcc9346c0a7f1007faea2c83d0e042c","cacheData":{"env":{}}}