{"dependencies":[{"name":"/Users/senecamac1/henry/playing-with-tensorflow/fitting-a-curve/package.json","includedInParent":true,"mtime":1522495589000},{"name":"/Users/senecamac1/henry/playing-with-tensorflow/fitting-a-curve/node_modules/vega-runtime/package.json","includedInParent":true,"mtime":1508906165000},{"name":"./expression","loc":{"line":1,"column":30}},{"name":"vega-util","loc":{"line":2,"column":20}}],"generated":{"js":"'use strict';\n\nObject.defineProperty(exports, \"__esModule\", {\n  value: true\n});\n\nexports.default = function (spec, ctx) {\n  var filter = spec.filter != null ? (0, _expression.eventExpression)(spec.filter, ctx) : undefined,\n      stream = spec.stream != null ? ctx.get(spec.stream) : undefined,\n      args;\n\n  if (spec.source) {\n    stream = ctx.events(spec.source, spec.type, filter);\n  } else if (spec.merge) {\n    args = spec.merge.map(ctx.get.bind(ctx));\n    stream = args[0].merge.apply(args[0], args.slice(1));\n  }\n\n  if (spec.between) {\n    args = spec.between.map(ctx.get.bind(ctx));\n    stream = stream.between(args[0], args[1]);\n  }\n\n  if (spec.filter) {\n    stream = stream.filter(filter);\n  }\n\n  if (spec.throttle != null) {\n    stream = stream.throttle(+spec.throttle);\n  }\n\n  if (spec.debounce != null) {\n    stream = stream.debounce(+spec.debounce);\n  }\n\n  if (stream == null) {\n    (0, _vegaUtil.error)('Invalid stream definition: ' + JSON.stringify(spec));\n  }\n\n  if (spec.consume) stream.consume(true);\n\n  ctx.stream(spec, stream);\n};\n\nvar _expression = require('./expression');\n\nvar _vegaUtil = require('vega-util');"},"hash":"7c18e318d4ec9d458aba929cc46560d9","cacheData":{"env":{}}}