{"dependencies":[{"name":"/Users/senecamac1/henry/playing-with-tensorflow/fitting-a-curve/package.json","includedInParent":true,"mtime":1522495589000},{"name":"/Users/senecamac1/henry/playing-with-tensorflow/fitting-a-curve/node_modules/vega-transforms/package.json","includedInParent":true,"mtime":1520278057000},{"name":"vega-dataflow","loc":{"line":1,"column":23}},{"name":"vega-util","loc":{"line":2,"column":32}}],"generated":{"js":"'use strict';\n\nObject.defineProperty(exports, \"__esModule\", {\n  value: true\n});\nexports.default = Compare;\n\nvar _vegaDataflow = require('vega-dataflow');\n\nvar _vegaUtil = require('vega-util');\n\n/**\n * Generates a comparator function.\n * @constructor\n * @param {object} params - The parameters for this operator.\n * @param {Array<string>} params.fields - The fields to compare.\n * @param {Array<string>} [params.orders] - The sort orders.\n *   Each entry should be one of \"ascending\" (default) or \"descending\".\n */\nfunction Compare(params) {\n  _vegaDataflow.Operator.call(this, null, update, params);\n}\n\n(0, _vegaUtil.inherits)(Compare, _vegaDataflow.Operator);\n\nfunction update(_) {\n  return this.value && !_.modified() ? this.value : (0, _vegaUtil.compare)(_.fields, _.orders);\n}"},"hash":"754cef7e4d1f551baeae38301a9ec435","cacheData":{"env":{}}}