{"dependencies":[{"name":"/Users/senecamac1/henry/playing-with-tensorflow/fitting-a-curve/package.json","includedInParent":true,"mtime":1522495589000},{"name":"/Users/senecamac1/henry/playing-with-tensorflow/fitting-a-curve/node_modules/@tensorflow/tfjs-core/package.json","includedInParent":true,"mtime":0}],"generated":{"js":"\"use strict\";\nObject.defineProperty(exports, \"__esModule\", { value: true });\nfunction doc(info) {\n    return function () {\n        var args = [];\n        for (var _i = 0; _i < arguments.length; _i++) {\n            args[_i] = arguments[_i];\n        }\n    };\n}\nexports.doc = doc;\n"},"hash":"51dd2770e7570034cb77c9b9a0415bc5","cacheData":{"env":{}}}