{"dependencies":[{"name":"/Users/senecamac1/henry/playing-with-tensorflow/fitting-a-curve/package.json","includedInParent":true,"mtime":1522495589000},{"name":"/Users/senecamac1/henry/playing-with-tensorflow/fitting-a-curve/node_modules/d3-format/package.json","includedInParent":true,"mtime":1515519070000},{"name":"./formatDefault","loc":{"line":1,"column":26}},{"name":"./formatPrefixAuto","loc":{"line":2,"column":29}},{"name":"./formatRounded","loc":{"line":3,"column":26}}],"generated":{"js":"\"use strict\";\n\nObject.defineProperty(exports, \"__esModule\", {\n  value: true\n});\n\nvar _formatDefault = require(\"./formatDefault\");\n\nvar _formatDefault2 = _interopRequireDefault(_formatDefault);\n\nvar _formatPrefixAuto = require(\"./formatPrefixAuto\");\n\nvar _formatPrefixAuto2 = _interopRequireDefault(_formatPrefixAuto);\n\nvar _formatRounded = require(\"./formatRounded\");\n\nvar _formatRounded2 = _interopRequireDefault(_formatRounded);\n\nfunction _interopRequireDefault(obj) { return obj && obj.__esModule ? obj : { default: obj }; }\n\nexports.default = {\n  \"\": _formatDefault2.default,\n  \"%\": function (x, p) {\n    return (x * 100).toFixed(p);\n  },\n  \"b\": function (x) {\n    return Math.round(x).toString(2);\n  },\n  \"c\": function (x) {\n    return x + \"\";\n  },\n  \"d\": function (x) {\n    return Math.round(x).toString(10);\n  },\n  \"e\": function (x, p) {\n    return x.toExponential(p);\n  },\n  \"f\": function (x, p) {\n    return x.toFixed(p);\n  },\n  \"g\": function (x, p) {\n    return x.toPrecision(p);\n  },\n  \"o\": function (x) {\n    return Math.round(x).toString(8);\n  },\n  \"p\": function (x, p) {\n    return (0, _formatRounded2.default)(x * 100, p);\n  },\n  \"r\": _formatRounded2.default,\n  \"s\": _formatPrefixAuto2.default,\n  \"X\": function (x) {\n    return Math.round(x).toString(16).toUpperCase();\n  },\n  \"x\": function (x) {\n    return Math.round(x).toString(16);\n  }\n};"},"hash":"e86a6a5020c4006bb98b0628079dc090","cacheData":{"env":{}}}